product_search_and_recommend/__init__.py
product_search_and_recommend/__main__.py
product_search_and_recommend/enums.py
product_search_and_recommend/models.py
product_search_and_recommend/server.py
product_search_and_recommend/service.py
product_search_and_recommend-0.3.0.dist-info/METADATA
product_search_and_recommend-0.3.0.dist-info/WHEEL
product_search_and_recommend-0.3.0.dist-info/entry_points.txt
product_search_and_recommend-0.3.0.dist-info/top_level.txt
product_search_and_recommend-0.3.0.dist-info/RECORD
