Metadata-Version: 2.4
Name: product_search_and_recommend
Version: 0.3.0
Summary: MCP server for product search and recommendation
Requires-Python: >=3.10
Requires-Dist: mcp>=1.0.0
Requires-Dist: pydantic>=2.0.0
